testforge_cli_utils/__init__.py
testforge_cli_utils/cli.py
testforge_cli_utils/config/__init__.py
testforge_cli_utils/config/config_loader.py
testforge_cli_utils/core/__init__.py
testforge_cli_utils/core/base_executor.py
testforge_cli_utils/core/executor.py
testforge_cli_utils/core/loader.py
testforge_cli_utils/core/logger.py
testforge_cli_utils/core/reporter.py
testforge_cli_utils/protocols/__init__.py
testforge_cli_utils/protocols/cxl.py
testforge_cli_utils/protocols/pcie.py
testforge_cli_utils/runner/__init__.py
testforge_cli_utils/runner/cxl_health_check_runner.py
testforge_cli_utils/tests/__init__.py
testforge_cli_utils/tests/health/__init__.py
testforge_cli_utils/tests/health/health.py
testforge_cli_utils/utils/__init__.py
testforge_cli_utils/utils/hardware_info.py
testforge_cli_utils/utils/host_check.py
testforge_cli_utils/utils/parser.py
testforge_cli_utils/utils/retry.py
testforge_cli_utils/utils/ssh.py
testforge_cli_utils/utils/ssh_command.py
testforge_cli_utils-0.1.5.dist-info/licenses/LICENSE
testforge_cli_utils-0.1.5.dist-info/METADATA
testforge_cli_utils-0.1.5.dist-info/WHEEL
testforge_cli_utils-0.1.5.dist-info/entry_points.txt
testforge_cli_utils-0.1.5.dist-info/top_level.txt
testforge_cli_utils-0.1.5.dist-info/RECORD
