Metadata-Version: 2.4
Name: testforge-cli-utils
Version: 0.1.5
Summary: Test Automation Framework for system-level validation (CXL, PCIe, BMC, firmware)
Home-page: https://github.com/MARIOREDFOX/TestForge
Author: Marie Infantraj
Author-email: Marie Infantraj <marioredfoxfshm@gmail.com>
License: GPL-3.0-or-later
Requires-Python: >=3.7
License-File: LICENSE
Requires-Dist: click
Requires-Dist: pyyaml
Requires-Dist: rich
Dynamic: author
Dynamic: license-file
Dynamic: requires-python
